etc/phantasy/config/demo_mconfig/accel/T30102-CM-000155-R001_20170724.xlsx
etc/phantasy/config/demo_mconfig/accel/channels.csv
etc/phantasy/config/demo_mconfig/accel/layout.csv
etc/phantasy/config/demo_mconfig/accel/phantasy.cfg
etc/phantasy/config/demo_mconfig/accel/phantasy.ini
etc/phantasy/config/demo_mconfig/accel/settings.json
etc/phantasy/config/demo_mconfig/accel/flame_data/axisData_41.txt
etc/phantasy/config/demo_mconfig/accel/flame_data/axisData_85.txt
etc/phantasy/config/demo_mconfig/accel/flame_data/envelope.txt
etc/phantasy/config/demo_mconfig/accel/flame_data/position.txt
etc/phantasy/config/demo_mconfig/accel/flame_data/Multipole41/CaviMlp_41.txt
etc/phantasy/config/demo_mconfig/accel/flame_data/Multipole41/thinlenlon_41.txt
etc/phantasy/config/demo_mconfig/accel/flame_data/Multipole85/CaviMlp_85.txt
etc/phantasy/config/demo_mconfig/accel/flame_data/Multipole85/thinlenlon_85.txt
phantasy/__init__.py
phantasy/config/element_fields.toml
phantasy/config/element_style.ini
phantasy/facility/__init__.py
phantasy/facility/frib/__init__.py
phantasy/facility/frib/_conf_std.py
phantasy/facility/frib/channels/__init__.py
phantasy/facility/frib/channels/channels.py
phantasy/facility/frib/channels/channels_ps.py
phantasy/facility/frib/channels/channels_pspv.py
phantasy/facility/frib/layout/__init__.py
phantasy/facility/frib/layout/fribxlf.py
phantasy/facility/frib/virtaccel/__init__.py
phantasy/facility/frib/virtaccel/flame.py
phantasy/facility/frib/virtaccel/impact.py
phantasy/library/__init__.py
phantasy/library/dconf.py
phantasy/library/channelfinder/__init__.py
phantasy/library/channelfinder/database.py
phantasy/library/channelfinder/io.py
phantasy/library/channelfinder/io_cfs.py
phantasy/library/channelfinder/store.py
phantasy/library/channelfinder/table.py
phantasy/library/data/__init__.py
phantasy/library/data/fit.py
phantasy/library/exception/__init__.py
phantasy/library/exception/err.py
phantasy/library/exception/exceptions.py
phantasy-2.2.8.dist-info/LICENSE
phantasy-2.2.8.dist-info/METADATA
phantasy-2.2.8.dist-info/WHEEL
phantasy-2.2.8.dist-info/entry_points.txt
phantasy-2.2.8.dist-info/top_level.txt
phantasy-2.2.8.dist-info/RECORD
